{
  "measured_at": "2026-05-07T01:26:17.231Z",
  "sample_size": 100,
  "failed": 0,
  "avg": 360,
  "p25": 294,
  "p50": 332,
  "p75": 412,
  "min": 231,
  "max": 819,
  "target_p50": 800,
  "pass": false,
  "pages": [
    {
      "slug": "스타필드시티-위례-주차장-KA-1935812519",
      "id": "KA-1935812519",
      "word_count": 585
    },
    {
      "slug": "청평면-임시공영주차장(1)-239-2-000018",
      "id": "239-2-000018",
      "word_count": 489
    },
    {
      "slug": "지족동-임시공영(1)-186-2-000057",
      "id": "186-2-000057",
      "word_count": 453
    },
    {
      "slug": "청평면-임시공영주차장(5)-239-2-000022",
      "id": "239-2-000022",
      "word_count": 486
    },
    {
      "slug": "궐동-제3공영주차장-223-2-000047",
      "id": "223-2-000047",
      "word_count": 471
    },
    {
      "slug": "청평면-임시공영주차장(4)-239-2-000021",
      "id": "239-2-000021",
      "word_count": 472
    },
    {
      "slug": "금학동-쌈지주차장(6)-286-2-000049",
      "id": "286-2-000049",
      "word_count": 403
    },
    {
      "slug": "청평면-임시공영주차장4-NV-1274115029_377317863",
      "id": "NV-1274115029_377317863",
      "word_count": 471
    },
    {
      "slug": "진곡일반산업단지-주차장11-179-2-000037",
      "id": "179-2-000037",
      "word_count": 389
    },
    {
      "slug": "진곡일반산업단지-주차장12-179-2-000038",
      "id": "179-2-000038",
      "word_count": 388
    },
    {
      "slug": "진곡일반산업단지7-공영주차장-KA-46082657",
      "id": "KA-46082657",
      "word_count": 394
    },
    {
      "slug": "진곡일반산업단지-주차장8-179-2-000034",
      "id": "179-2-000034",
      "word_count": 387
    },
    {
      "slug": "진곡일반산업단지-주차장10-179-2-000036",
      "id": "179-2-000036",
      "word_count": 425
    },
    {
      "slug": "가평읍-노상주차장-7구간-239-1-000008",
      "id": "239-1-000008",
      "word_count": 408
    },
    {
      "slug": "가평읍-노상주차장-8구간-239-1-000009",
      "id": "239-1-000009",
      "word_count": 404
    },
    {
      "slug": "옥천공영주차타워-276-2-000004",
      "id": "276-2-000004",
      "word_count": 356
    },
    {
      "slug": "진곡일반산업단지9-공영주차장-KA-30109508",
      "id": "KA-30109508",
      "word_count": 418
    },
    {
      "slug": "진곡일반산업단지13-공영주차장-KA-36857965",
      "id": "KA-36857965",
      "word_count": 418
    },
    {
      "slug": "상림공원-주차장-KA-17562389",
      "id": "KA-17562389",
      "word_count": 470
    },
    {
      "slug": "상번천리-공영주차장-234-2-000016",
      "id": "234-2-000016",
      "word_count": 353
    },
    {
      "slug": "송정동-크로바쇼핑-인근-공영주차장-234-1-000007",
      "id": "234-1-000007",
      "word_count": 338
    },
    {
      "slug": "가평읍-노상주차장-5구간-239-1-000005",
      "id": "239-1-000005",
      "word_count": 373
    },
    {
      "slug": "가평읍-임시공영주차장(5)-239-2-000013",
      "id": "239-2-000013",
      "word_count": 332
    },
    {
      "slug": "가평읍-임시공영주차장(6)-239-2-000014",
      "id": "239-2-000014",
      "word_count": 326
    },
    {
      "slug": "가평읍-임시공영주차장(7)-239-2-000015",
      "id": "239-2-000015",
      "word_count": 319
    },
    {
      "slug": "청평면-공영주차장-KA-530907043",
      "id": "KA-530907043",
      "word_count": 463
    },
    {
      "slug": "행주산성-제1주차장-KA-20588761",
      "id": "KA-20588761",
      "word_count": 377
    },
    {
      "slug": "예천동-1698-공영주차장-289-2-000187",
      "id": "289-2-000187",
      "word_count": 355
    },
    {
      "slug": "수원시청-별관-주차장-KA-110453478",
      "id": "KA-110453478",
      "word_count": 541
    },
    {
      "slug": "광주송정역-4주차장-KA-1426498004",
      "id": "KA-1426498004",
      "word_count": 776
    },
    {
      "slug": "금산로2공영주차장-225-1-000004",
      "id": "225-1-000004",
      "word_count": 288
    },
    {
      "slug": "문화공영주차장-225-2-000044",
      "id": "225-2-000044",
      "word_count": 266
    },
    {
      "slug": "가평읍-노상주차장-1구간-239-1-000001",
      "id": "239-1-000001",
      "word_count": 314
    },
    {
      "slug": "양평읍노상유료주차장-240-1-000001",
      "id": "240-1-000001",
      "word_count": 260
    },
    {
      "slug": "천년고성시장-주차장-266-2-000003",
      "id": "266-2-000003",
      "word_count": 265
    },
    {
      "slug": "동구공영주차빌딩-132-2-000003",
      "id": "132-2-000003",
      "word_count": 465
    },
    {
      "slug": "군포역환승공영주차장-225-2-000039",
      "id": "225-2-000039",
      "word_count": 300
    },
    {
      "slug": "군포역환승공영주차장-KA-24066475",
      "id": "KA-24066475",
      "word_count": 300
    },
    {
      "slug": "선부동-주택가주차장-217-2-000031",
      "id": "217-2-000031",
      "word_count": 398
    },
    {
      "slug": "선부동-주택가주차장-217-2-000032",
      "id": "217-2-000032",
      "word_count": 398
    },
    {
      "slug": "성산-노외2-공영주차장-406-2-000097",
      "id": "406-2-000097",
      "word_count": 333
    },
    {
      "slug": "수원시청-제2부설주차장-KA-11495150",
      "id": "KA-11495150",
      "word_count": 527
    },
    {
      "slug": "구로디지털단지역-공영주차장-KA-1108867781",
      "id": "KA-1108867781",
      "word_count": 257
    },
    {
      "slug": "구로디지털단지역-공영주차장-KA-27199541",
      "id": "KA-27199541",
      "word_count": 257
    },
    {
      "slug": "시네마주차장-175-4-000116",
      "id": "175-4-000116",
      "word_count": 437
    },
    {
      "slug": "GTX-A-운정중앙역2-229-2-000092",
      "id": "229-2-000092",
      "word_count": 350
    },
    {
      "slug": "송정동(구)우시장-공영주차장-234-2-000004",
      "id": "234-2-000004",
      "word_count": 294
    },
    {
      "slug": "가평읍-노상주차장-2구간-239-1-000002",
      "id": "239-1-000002",
      "word_count": 313
    },
    {
      "slug": "가평읍-노상주차장-4구간-239-1-000004",
      "id": "239-1-000004",
      "word_count": 306
    },
    {
      "slug": "가평읍-임시공영주차장(4)-239-2-000012",
      "id": "239-2-000012",
      "word_count": 294
    },
    {
      "slug": "선교장-환승주차장-252-2-000048",
      "id": "252-2-000048",
      "word_count": 272
    },
    {
      "slug": "고상아리1길-주차장-286-1-000015",
      "id": "286-1-000015",
      "word_count": 243
    },
    {
      "slug": "금학동-쌈지주차장-286-2-000072",
      "id": "286-2-000072",
      "word_count": 315
    },
    {
      "slug": "금학동-쌈지주차장-286-2-000076",
      "id": "286-2-000076",
      "word_count": 317
    },
    {
      "slug": "하양읍-하양로-360-1-000105",
      "id": "360-1-000105",
      "word_count": 457
    },
    {
      "slug": "호계역1공영주차장-KA-20588941",
      "id": "KA-20588941",
      "word_count": 305
    },
    {
      "slug": "강릉선교장-공영주차장-KA-253007880",
      "id": "KA-253007880",
      "word_count": 271
    },
    {
      "slug": "논현로28길-노상공영주차장-KA-17772274",
      "id": "KA-17772274",
      "word_count": 428
    },
    {
      "slug": "궐동공영주차장-223-3-000005",
      "id": "223-3-000005",
      "word_count": 317
    },
    {
      "slug": "예천동-1257-2-임시공영주차장-289-2-000167",
      "id": "289-2-000167",
      "word_count": 266
    },
    {
      "slug": "취암동-1082-1번지-임시공영주차장-290-2-000075",
      "id": "290-2-000075",
      "word_count": 283
    },
    {
      "slug": "서울고속버스터미널-사잇길주차장-KA-1597963698",
      "id": "KA-1597963698",
      "word_count": 462
    },
    {
      "slug": "인천국제공항-제2여객터미널-예약주차장-KA-878648043",
      "id": "KA-878648043",
      "word_count": 367
    },
    {
      "slug": "탄현-제2-219-2-000003",
      "id": "219-2-000003",
      "word_count": 418
    },
    {
      "slug": "하양읍-대경로-360-1-000102",
      "id": "360-1-000102",
      "word_count": 412
    },
    {
      "slug": "호계역2공영주차장-KA-292946712",
      "id": "KA-292946712",
      "word_count": 306
    },
    {
      "slug": "중앙시장-제3공영주차장-183-2-000028",
      "id": "183-2-000028",
      "word_count": 321
    },
    {
      "slug": "온덕-196-2-000028",
      "id": "196-2-000028",
      "word_count": 329
    },
    {
      "slug": "합천읍-공영주차장-398-2-000048",
      "id": "398-2-000048",
      "word_count": 484
    },
    {
      "slug": "영등포구청역-공영주차장-KA-25620337",
      "id": "KA-25620337",
      "word_count": 819
    },
    {
      "slug": "온천동-제2공영주차장-288-2-000012",
      "id": "288-2-000012",
      "word_count": 318
    },
    {
      "slug": "나성동-공영주차장-413-2-000064",
      "id": "413-2-000064",
      "word_count": 333
    },
    {
      "slug": "황성동-갓뒤마을-공용주차장-352-2-000079",
      "id": "352-2-000079",
      "word_count": 342
    },
    {
      "slug": "우보면4노상주차장-361-1-000008",
      "id": "361-1-000008",
      "word_count": 307
    },
    {
      "slug": "사우자주식-공영주차장-KA-11487068",
      "id": "KA-11487068",
      "word_count": 271
    },
    {
      "slug": "입암면종합복지회관주차장-NV-1290898912_365939853",
      "id": "NV-1290898912_365939853",
      "word_count": 347
    },
    {
      "slug": "도당공원1-000-3-000002",
      "id": "000-3-000002",
      "word_count": 288
    },
    {
      "slug": "솔마루어린이공원공영주차장-162-2-000004",
      "id": "162-2-000004",
      "word_count": 272
    },
    {
      "slug": "연수3동-공영주차장-164-2-000001",
      "id": "164-2-000001",
      "word_count": 307
    },
    {
      "slug": "북구문화센터-공영주차장-178-2-000083",
      "id": "178-2-000083",
      "word_count": 231
    },
    {
      "slug": "미관광장-224-2-000005",
      "id": "224-2-000005",
      "word_count": 252
    },
    {
      "slug": "월롱역-환승주차장-229-2-000081",
      "id": "229-2-000081",
      "word_count": 274
    },
    {
      "slug": "신관동-공영주차장-286-2-000007",
      "id": "286-2-000007",
      "word_count": 297
    },
    {
      "slug": "금학동-공영주차장-286-2-000012",
      "id": "286-2-000012",
      "word_count": 321
    },
    {
      "slug": "백운호수제방-공영주차장-226-2-000007",
      "id": "226-2-000007",
      "word_count": 295
    },
    {
      "slug": "오색그린야드호텔주차장-267-4-000012",
      "id": "267-4-000012",
      "word_count": 301
    },
    {
      "slug": "예천동-524-9-임시공영주차장-289-2-000143",
      "id": "289-2-000143",
      "word_count": 260
    },
    {
      "slug": "예천동-1275-2-임시공영주차장-289-2-000171",
      "id": "289-2-000171",
      "word_count": 268
    },
    {
      "slug": "오이도-노상-공영-주차장-NV-1266880183_373464188",
      "id": "NV-1266880183_373464188",
      "word_count": 368
    },
    {
      "slug": "이천남천상가-공영주차장-NV-1274445912_372780810",
      "id": "NV-1274445912_372780810",
      "word_count": 232
    },
    {
      "slug": "광지원리-교량-하부-공영주차장-234-2-000021",
      "id": "234-2-000021",
      "word_count": 293
    },
    {
      "slug": "삼문동-공영주차장-KA-95854611",
      "id": "KA-95854611",
      "word_count": 331
    },
    {
      "slug": "추동-캠핑카-전용-공영주차장-207-2-000051",
      "id": "207-2-000051",
      "word_count": 293
    },
    {
      "slug": "금구천-하상주차장-276-2-000001",
      "id": "276-2-000001",
      "word_count": 456
    },
    {
      "slug": "배방읍-공수리-제1공영주차장-288-2-000018",
      "id": "288-2-000018",
      "word_count": 332
    },
    {
      "slug": "신성동-주민센터앞-임시공영-186-2-000056",
      "id": "186-2-000056",
      "word_count": 384
    },
    {
      "slug": "향남-하길리-233-2-000103",
      "id": "233-2-000103",
      "word_count": 325
    },
    {
      "slug": "장재리-제1공영주차장-288-2-000051",
      "id": "288-2-000051",
      "word_count": 285
    },
    {
      "slug": "영등동-공영주차장-308-2-000002",
      "id": "308-2-000002",
      "word_count": 255
    },
    {
      "slug": "벌교읍사무소주차장-333-3-000013",
      "id": "333-3-000013",
      "word_count": 334
    }
  ]
}